CONTRIBUTORS
LICENSE
MANIFEST.in
README.rst
setup.py
strawboss/__init__.py
strawboss/version.txt
strawboss.egg-info/PKG-INFO
strawboss.egg-info/SOURCES.txt
strawboss.egg-info/dependency_links.txt
strawboss.egg-info/entry_points.txt
strawboss.egg-info/requires.txt
strawboss.egg-info/top_level.txt
tests/__init__.py
tests/conftest.py
tests/test_cli.py
tests/test_main.py
tests/test_run.py
tests/test_utils.py