Metadata-Version: 1.1
Name: strawboss
Version: 0.2.0
Summary: Procfile runner
Home-page: https://github.com/smartmob-project/strawboss
Author: Andre Caron
Author-email: ac@smartmob.org
License: MIT
Keywords: procfile asyncio foreman honcho
Platform: UNKNOWN
Classifier: Development Status :: 1 - Planning
Classifier: Intended Audience :: Developers
Classifier: License :: OSI Approved :: MIT License
Classifier: Operating System :: MacOS :: MacOS X
Classifier: Programming Language :: Python
Classifier: Programming Language :: Python :: 3.5
Classifier: Topic :: Software Development :: Libraries
